LICENSE
MANIFEST.in
README.md
requirements.txt
setup.py
quantiphyse_deeds/__init__.py
quantiphyse_deeds/_version.py
quantiphyse_deeds/deeds_wrapper.cpp
quantiphyse_deeds/deeds_wrapper.pyx
quantiphyse_deeds/method.py
quantiphyse_deeds/tests.py
quantiphyse_deeds.egg-info/PKG-INFO
quantiphyse_deeds.egg-info/SOURCES.txt
quantiphyse_deeds.egg-info/dependency_links.txt
quantiphyse_deeds.egg-info/entry_points.txt
quantiphyse_deeds.egg-info/requires.txt
quantiphyse_deeds.egg-info/top_level.txt
quantiphyse_deeds/src/TMI2013/MIND-SSC.h
quantiphyse_deeds/src/TMI2013/TMI_MINDSSC.cpp
quantiphyse_deeds/src/TMI2013/TMI_SAD.cpp
quantiphyse_deeds/src/TMI2013/TMI_deformation.cpp
quantiphyse_deeds/src/TMI2013/applyWarp.cpp
quantiphyse_deeds/src/TMI2013/dataCostD.h
quantiphyse_deeds/src/TMI2013/dataCostD_mind.h
quantiphyse_deeds/src/TMI2013/deedsMSTsad.h
quantiphyse_deeds/src/TMI2013/deedsMSTssc.cpp
quantiphyse_deeds/src/TMI2013/deedsMSTssc.h
quantiphyse_deeds/src/TMI2013/deeds_thread.h
quantiphyse_deeds/src/TMI2013/fastdt2.h
quantiphyse_deeds/src/TMI2013/niftiIO.h
quantiphyse_deeds/src/TMI2013/primsMST.h
quantiphyse_deeds/src/TMI2013/regularisation2T.h
quantiphyse_deeds/src/TMI2013/resizeFlow.h
quantiphyse_deeds/src/TMI2013/symmetricDiffeomorphic.h
quantiphyse_deeds/src/WBIR2014/MIND-SSClowres.h
quantiphyse_deeds/src/WBIR2014/WBIR_LCC.cpp
quantiphyse_deeds/src/WBIR2014/WBIR_SSC.cpp
quantiphyse_deeds/src/WBIR2014/WBIR_deformation.cpp
quantiphyse_deeds/src/WBIR2014/boxfilter4.h
quantiphyse_deeds/src/WBIR2014/dataCostLCC.h
quantiphyse_deeds/src/WBIR2014/dataCostSSC.h
quantiphyse_deeds/src/WBIR2014/deeds2deformation.h
quantiphyse_deeds/src/WBIR2014/deedsConvexLCC.h
quantiphyse_deeds/src/WBIR2014/deedsConvexSSC.h
quantiphyse_deeds/src/WBIR2014/inverseMapping.h
quantiphyse_deeds/src/WBIR2014/niftiIO.h
quantiphyse_deeds/src/WBIR2014/smoothCost.h
quantiphyse_deeds/src/WBIR2014/transformations.h
quantiphyse_deeds/src/compat/stdint.h